noloox/cluster/__init__.py
noloox/cluster/peax.py
noloox/decomposition/__init__.py
noloox/decomposition/snmf.py
noloox/decomposition/wnmf.py
noloox/manifold/_ptsne.py
noloox/manifold/ptsne.py
noloox/mixture/__init__.py
noloox/mixture/_dmm.py
noloox/mixture/dmm.py
noloox/mixture/tmm.py
noloox-0.1.0.dist-info/LICENSE
noloox-0.1.0.dist-info/METADATA
noloox-0.1.0.dist-info/WHEEL
noloox-0.1.0.dist-info/RECORD
