Metadata-Version: 2.3
Name: noloox
Version: 0.1.0
Summary: Unsupervised learning algorithms you will need one day.
License: MIT
Author: Márton Kardos
Author-email: power.up1163@gmail.com
Requires-Python: >=3.11
Classifier: License :: OSI Approved :: MIT License
Classifier: Programming Language :: Python :: 3
Classifier: Programming Language :: Python :: 3.11
Classifier: Programming Language :: Python :: 3.12
Classifier: Programming Language :: Python :: 3.13
Provides-Extra: docs
Requires-Dist: griffe (==0.40.0) ; extra == "docs"
Requires-Dist: jax (>=0.8.0,<0.9.0)
Requires-Dist: mkdocs (==1.6.1) ; extra == "docs"
Requires-Dist: mkdocs-autorefs (==0.5.0) ; extra == "docs"
Requires-Dist: mkdocs-material (==9.6.19) ; extra == "docs"
Requires-Dist: mkdocs-material-extensions (==1.3.1) ; extra == "docs"
Requires-Dist: mkdocstrings (==0.22.0) ; extra == "docs"
Requires-Dist: mkdocstrings-python (==1.8.0) ; extra == "docs"
Requires-Dist: numpy (>=2.0.0)
Requires-Dist: scikit-learn (>=1.3.0,<2.0.0)
Requires-Dist: scipy (>=1.16.0,<2.0.0)
Requires-Dist: tqdm (>=4.0.0,<5.0.0)
